{
  " ": {
    "id": "minecraft:air",
    "properties": {}
  },
  "A": {
    "id": "gtocore:industrial_platform_deployment_tools",
    "properties": {
      "facing": "north"
    }
  },
  "B": {
    "id": "minecraft:water",
    "properties": {
      "level": "0"
    }
  },
  "C": {
    "id": "minecraft:packed_ice",
    "properties": {}
  },
  "D": {
    "id": "minecraft:blue_ice",
    "properties": {}
  },
  "E": {
    "id": "minecraft:dirt",
    "properties": {}
  },
  "F": {
    "id": "minecraft:sand",
    "properties": {}
  },
  "G": {
    "id": "minecraft:granite",
    "properties": {}
  },
  "H": {
    "id": "minecraft:sandstone",
    "properties": {}
  },
  "I": {
    "id": "gtceu:oil_medium",
    "properties": {
      "level": "0"
    }
  },
  "J": {
    "id": "minecraft:gravel",
    "properties": {}
  },
  "K": {
    "id": "minecraft:magma_block",
    "properties": {}
  },
  "L": {
    "id": "minecraft:bubble_column",
    "properties": {
      "drag": "true"
    }
  },
  "M": {
    "id": "minecraft:ice",
    "properties": {}
  },
  "N": {
    "id": "minecraft:snow",
    "properties": {
      "layers": "1"
    }
  },
  "O": {
    "id": "gtceu:apatite_indicator",
    "properties": {
      "facing": "down"
    }
  },
  "P": {
    "id": "gtceu:oil_medium",
    "properties": {
      "level": "7"
    }
  },
  "Q": {
    "id": "gtceu:oil_medium",
    "properties": {
      "level": "6"
    }
  },
  "R": {
    "id": "gtceu:oil_medium",
    "properties": {
      "level": "5"
    }
  },
  "S": {
    "id": "gtceu:oil_medium",
    "properties": {
      "level": "4"
    }
  },
  "T": {
    "id": "gtceu:oil_medium",
    "properties": {
      "level": "3"
    }
  },
  "U": {
    "id": "gtceu:oil_medium",
    "properties": {
      "level": "2"
    }
  },
  "V": {
    "id": "gtceu:oil_medium",
    "properties": {
      "level": "1"
    }
  },
  "W": {
    "id": "minecraft:snow_block",
    "properties": {}
  },
  "X": {
    "id": "gtceu:oil_medium",
    "properties": {
      "level": "8"
    }
  },
  "Y": {
    "id": "minecraft:stone",
    "properties": {}
  },
  "Z": {
    "id": "gtocore:industrial_platform_deployment_tools",
    "properties": {
      "facing": "east"
    }
  }
}